{
    "BeatFraction.Breve|block": "",
    "BeatFraction.Double|block": "",
    "BeatFraction.Eighth|block": "",
    "BeatFraction.Half|block": "",
    "BeatFraction.Quarter|block": "",
    "BeatFraction.Sixteenth|block": "",
    "BeatFraction.Whole|block": "",
    "Note.CSharp3|block": "",
    "Note.CSharp4|block": "",
    "Note.CSharp5|block": "",
    "Note.CSharp|block": "",
    "Note.FSharp3|block": "",
    "Note.FSharp4|block": "",
    "Note.FSharp5|block": "",
    "Note.FSharp|block": "",
    "Note.GSharp3|block": "",
    "Note.GSharp4|block": "",
    "Note.GSharp5|block": "",
    "Note.GSharp|block": "",
    "SoundOutputDestination.Pin|block": "",
    "SoundOutputDestination.Speaker|block": "",
    "music.beat|block": "",
    "music.changeTempoBy|block": "",
    "music.noteFrequency|block": "",
    "music.playSoundEffectUntilDone|block": "",
    "music.playSoundEffect|block": "",
    "music.playTone|block": "",
    "music.rest|block": "",
    "music.ringTone|block": "",
    "music.setTempo|block": "",
    "music.setVolume|block": "",
    "music.stopAllSounds|block": "",
    "music.tempo|block": "",
    "music|block": "",
    "sounds.animalsCatPurr|block": "",
    "sounds.animalsDogBark1|block": "",
    "sounds.animalsDogBark2|block": "",
    "sounds.animalsDogGrowl|block": "",
    "sounds.animalsDogSniff|block": "",
    "sounds.animalsDogWhine|block": "",
    "sounds.animalsElephantCall|block": "",
    "sounds.animalsInsectBuzz1|block": "",
    "sounds.animalsInsectBuzz2|block": "",
    "sounds.animalsInsectChirp|block": "",
    "sounds.animalsSnakeHiss|block": "",
    "sounds.animalsSnakeRattle|block": "",
    "sounds.animalsTRexRoar|block": "",
    "sounds.colorsBlack|block": "",
    "sounds.colorsBlue|block": "",
    "sounds.colorsBrown|block": "",
    "sounds.colorsGreen|block": "",
    "sounds.colorsRed|block": "",
    "sounds.colorsWhite|block": "",
    "sounds.colorsYellow|block": "",
    "sounds.communicationBravo|block": "",
    "sounds.communicationEv3|block": "",
    "sounds.communicationFantastic|block": "",
    "sounds.communicationGameOver|block": "",
    "sounds.communicationGoodJob|block": "",
    "sounds.communicationGoodbye|block": "",
    "sounds.communicationGood|block": "",
    "sounds.communicationGo|block": "",
    "sounds.communicationHello|block": "",
    "sounds.communicationHi|block": "",
    "sounds.communicationLego|block": "",
    "sounds.communicationMindstorms|block": "",
    "sounds.communicationMorning|block": "",
    "sounds.communicationNo|block": "",
    "sounds.communicationOkay|block": "",
    "sounds.communicationOkeyDokey|block": "",
    "sounds.communicationSorry|block": "",
    "sounds.communicationThankYou|block": "",
    "sounds.communicationYes|block": "",
    "sounds.expressionsBoing|block": "",
    "sounds.expressionsBoo|block": "",
    "sounds.expressionsCheering|block": "",
    "sounds.expressionsCrunching|block": "",
    "sounds.expressionsCrying|block": "",
    "sounds.expressionsFanfare|block": "",
    "sounds.expressionsKungFu|block": "",
    "sounds.expressionsLaughing1|block": "",
    "sounds.expressionsLaughing2|block": "",
    "sounds.expressionsMagicWand|block": "",
    "sounds.expressionsOuch|block": "",
    "sounds.expressionsShouting|block": "",
    "sounds.expressionsSmack|block": "",
    "sounds.expressionsSneezing|block": "",
    "sounds.expressionsSnoring|block": "",
    "sounds.expressionsUhOh|block": "",
    "sounds.informationActivate|block": "",
    "sounds.informationAnalyze|block": "",
    "sounds.informationBackwards|block": "",
    "sounds.informationColor|block": "",
    "sounds.informationDetected|block": "",
    "sounds.informationDown|block": "",
    "sounds.informationErrorAlarm|block": "",
    "sounds.informationError|block": "",
    "sounds.informationFlashing|block": "",
    "sounds.informationForward|block": "",
    "sounds.informationLeft|block": "",
    "sounds.informationObject|block": "",
    "sounds.informationRight|block": "",
    "sounds.informationSearching|block": "",
    "sounds.informationStart|block": "",
    "sounds.informationStop|block": "",
    "sounds.informationTouch|block": "",
    "sounds.informationTurn|block": "",
    "sounds.informationUp|block": "",
    "sounds.mechanicalAirRelease|block": "",
    "sounds.mechanicalAirbrake|block": "",
    "sounds.mechanicalBackingAlert|block": "",
    "sounds.mechanicalBlip1|block": "",
    "sounds.mechanicalBlip2|block": "",
    "sounds.mechanicalBlip3|block": "",
    "sounds.mechanicalBlip4|block": "",
    "sounds.mechanicalHorn1|block": "",
    "sounds.mechanicalHorn2|block": "",
    "sounds.mechanicalLaser|block": "",
    "sounds.mechanicalMotorIdle|block": "",
    "sounds.mechanicalMotorStart|block": "",
    "sounds.mechanicalMotorStop|block": "",
    "sounds.mechanicalRatchet|block": "",
    "sounds.mechanicalSonar|block": "",
    "sounds.mechanicalTickTack|block": "",
    "sounds.mechanicalWalk|block": "",
    "sounds.movementsArm1|block": "",
    "sounds.movementsArm2|block": "",
    "sounds.movementsArm3|block": "",
    "sounds.movementsArm4|block": "",
    "sounds.movementsDropLoad|block": "",
    "sounds.movementsLiftLoad|block": "",
    "sounds.movementsServo1|block": "",
    "sounds.movementsServo2|block": "",
    "sounds.movementsServo3|block": "",
    "sounds.movementsServo4|block": "",
    "sounds.movementsSlideLoad|block": "",
    "sounds.movementsSnap|block": "",
    "sounds.movementsSpeedDown|block": "",
    "sounds.movementsSpeedIdle|block": "",
    "sounds.movementsSpeedUp|block": "",
    "sounds.movementsSpeeding|block": "",
    "sounds.numbersEight|block": "",
    "sounds.numbersFive|block": "",
    "sounds.numbersFour|block": "",
    "sounds.numbersNine|block": "",
    "sounds.numbersOne|block": "",
    "sounds.numbersSeven|block": "",
    "sounds.numbersSix|block": "",
    "sounds.numbersTen|block": "",
    "sounds.numbersThree|block": "",
    "sounds.numbersTwo|block": "",
    "sounds.numbersZero|block": "",
    "sounds.systemClick|block": "",
    "sounds.systemConfirm|block": "",
    "sounds.systemConnect|block": "",
    "sounds.systemDownload|block": "",
    "sounds.systemGeneralAlert|block": "",
    "sounds.systemOverpower|block": "",
    "sounds.systemPowerDown|block": "",
    "sounds.systemReady|block": "",
    "sounds.systemStartUp|block": "",
    "{id:category}Music": "",
    "{id:category}Sound": "",
    "{id:category}Sounds": ""
}